nvidia/__init__.py
nvidia/nvcomp/__init__.py
nvidia/nvcomp/external_memory.py
nvidia/nvcomp/nvcomp64_5.dll
nvidia/nvcomp/nvcomp_impl.cp310-win_amd64.pyd
nvidia/nvcomp/nvcomp_impl.cp311-win_amd64.pyd
nvidia/nvcomp/nvcomp_impl.cp312-win_amd64.pyd
nvidia/nvcomp/nvcomp_impl.cp313-win_amd64.pyd
nvidia/nvcomp/nvcomp_impl.cp38-win_amd64.pyd
nvidia/nvcomp/nvcomp_impl.cp39-win_amd64.pyd
nvidia/nvcomp/include/nvcomp.h
nvidia/nvcomp/include/nvcomp.hpp
nvidia/nvcomp/include/nvcomp/ans.h
nvidia/nvcomp/include/nvcomp/ans.hpp
nvidia/nvcomp/include/nvcomp/bitcomp.h
nvidia/nvcomp/include/nvcomp/bitcomp.hpp
nvidia/nvcomp/include/nvcomp/cascaded.h
nvidia/nvcomp/include/nvcomp/cascaded.hpp
nvidia/nvcomp/include/nvcomp/crc32.h
nvidia/nvcomp/include/nvcomp/deflate.h
nvidia/nvcomp/include/nvcomp/deflate.hpp
nvidia/nvcomp/include/nvcomp/gdeflate.h
nvidia/nvcomp/include/nvcomp/gdeflate.hpp
nvidia/nvcomp/include/nvcomp/gzip.h
nvidia/nvcomp/include/nvcomp/gzip.hpp
nvidia/nvcomp/include/nvcomp/lz4.h
nvidia/nvcomp/include/nvcomp/lz4.hpp
nvidia/nvcomp/include/nvcomp/nvcompManager.hpp
nvidia/nvcomp/include/nvcomp/nvcompManagerFactory.hpp
nvidia/nvcomp/include/nvcomp/shared_types.h
nvidia/nvcomp/include/nvcomp/snappy.h
nvidia/nvcomp/include/nvcomp/snappy.hpp
nvidia/nvcomp/include/nvcomp/utils.hpp
nvidia/nvcomp/include/nvcomp/zstd.h
nvidia/nvcomp/include/nvcomp/zstd.hpp
nvidia/nvcomp/include/nvcomp/native/bitcomp.h
nvidia/nvcomp/include/nvcomp/native/gdeflate_cpu.h
nvidia_nvcomp_cu12-5.0.0.6.dist-info/licenses/LICENSE
nvidia_nvcomp_cu12-5.0.0.6.dist-info/licenses/NOTICE
nvidia_nvcomp_cu12-5.0.0.6.dist-info/METADATA
nvidia_nvcomp_cu12-5.0.0.6.dist-info/WHEEL
nvidia_nvcomp_cu12-5.0.0.6.dist-info/top_level.txt
nvidia_nvcomp_cu12-5.0.0.6.dist-info/RECORD
