Metadata-Version: 2.4
Name: nvidia-nvcomp-cu12
Version: 5.0.0.6
Summary: NVIDIA nvcomp for CUDA 12. Git SHA: 
Home-page: https://developer.nvidia.com/nvcomp
Author: NVIDIA Corporation
License: LICENSE AGREEMENT FOR NVIDIA SOFTWARE DEVELOPMENT KITS
Classifier: Programming Language :: Python :: 3.8
Classifier: Programming Language :: Python :: 3.9
Classifier: Programming Language :: Python :: 3.10
Classifier: Programming Language :: Python :: 3.11
Classifier: Programming Language :: Python :: 3.12
Classifier: Programming Language :: Python :: 3.13
Requires-Python: >=3.8, <3.14
License-File: LICENSE
License-File: NOTICE
Dynamic: author
Dynamic: classifier
Dynamic: description
Dynamic: description-content-type
Dynamic: home-page
Dynamic: license
Dynamic: license-file
Dynamic: requires-python
Dynamic: summary
